torchgdm/__init__.py
torchgdm/constants.py
torchgdm/field.py
torchgdm/linearsystem.py
torchgdm/simulation.py
torchgdm/env/__init__.py
torchgdm/env/base_classes.py
torchgdm/env/freespace_2d/__init__.py
torchgdm/env/freespace_2d/dyads.py
torchgdm/env/freespace_2d/inc_fields.py
torchgdm/env/freespace_3d/__init__.py
torchgdm/env/freespace_3d/_dyads_numpy.py
torchgdm/env/freespace_3d/dyads.py
torchgdm/env/freespace_3d/inc_fields.py
torchgdm/materials/__init__.py
torchgdm/materials/base_classes.py
torchgdm/materials/hardcoded.py
torchgdm/materials/tabulated.py
torchgdm/materials/data/Ag_Johnson1972.yml
torchgdm/materials/data/Al2O3e_Malitson1972.yml
torchgdm/materials/data/Al2O3o_Malitson1972.yml
torchgdm/materials/data/Al_Rakic1995.yml
torchgdm/materials/data/Au_Johnson1972.yml
torchgdm/materials/data/GaAs_Papatryfonos2021.yml
torchgdm/materials/data/GaN_Kawashima1997.yml
torchgdm/materials/data/GaP_Aspnes1983.yml
torchgdm/materials/data/Ge_Nunley2016.yml
torchgdm/materials/data/InAs_Aspnes1983.yml
torchgdm/materials/data/InP_Aspnes1983.yml
torchgdm/materials/data/Si3N4_Luke2015.yml
torchgdm/materials/data/SiO2_Malitson1965.yml
torchgdm/materials/data/Si_Schinke2015.yml
torchgdm/materials/data/TiO2_Devore1965.yml
torchgdm/materials/data/ZrO2_Wood1982.yml
torchgdm/materials/data/aSi_Pierce1972.yml
torchgdm/postproc/__init__.py
torchgdm/postproc/crosssect.py
torchgdm/postproc/fields.py
torchgdm/postproc/green.py
torchgdm/postproc/multipole.py
torchgdm/struct/__init__.py
torchgdm/struct/base_classes.py
torchgdm/struct/eff_model_tools.py
torchgdm/struct/struct2d/__init__.py
torchgdm/struct/struct2d/geometries.py
torchgdm/struct/struct2d/gpm2d.py
torchgdm/struct/struct2d/line.py
torchgdm/struct/struct2d/surface.py
torchgdm/struct/struct3d/__init__.py
torchgdm/struct/struct3d/geometries.py
torchgdm/struct/struct3d/gpm3d.py
torchgdm/struct/struct3d/point.py
torchgdm/struct/struct3d/volume.py
torchgdm/tools/__init__.py
torchgdm/tools/batch.py
torchgdm/tools/geometry.py
torchgdm-0.56.dist-info/licenses/LICENSE.txt
torchgdm-0.56.dist-info/METADATA
torchgdm-0.56.dist-info/WHEEL
torchgdm-0.56.dist-info/top_level.txt
torchgdm-0.56.dist-info/RECORD
