Metadata-Version: 2.4
Name: torchgdm
Version: 0.56
Summary: Nano-optics + autodiff. Full field scattering simulations in pytorch.
Author-email: "Peter R. Wiecha" <pwiecha@laas.fr>
Maintainer-email: "Peter R. Wiecha" <pwiecha@laas.fr>
License-Expression: GPL-3.0-or-later
Project-URL: Homepage, https://homepages.laas.fr/pwiecha/torchgdm_doc/
Project-URL: Bug Reports, https://gitlab.com/wiechapeter/torchgdm/-/issues
Project-URL: Source, https://gitlab.com/wiechapeter/torchgdm
Keywords: volume integral method,green dyadic method,coupled dipoles method,effective polarizabilities,electrodynamical simulations,nano optics,frequency-domain,automatic differentiation
Classifier: Development Status :: 4 - Beta
Classifier: Intended Audience :: Science/Research
Classifier: Topic :: Scientific/Engineering
Classifier: Topic :: Scientific/Engineering :: Physics
Classifier: Topic :: Scientific/Engineering :: Astronomy
Classifier: Topic :: Scientific/Engineering :: Atmospheric Science
Classifier: Programming Language :: Python :: 3.9
Classifier: Programming Language :: Python :: 3.10
Classifier: Programming Language :: Python :: 3.11
Classifier: Programming Language :: Python :: 3.12
Requires-Python: >=3.9
License-File: LICENSE.txt
Requires-Dist: torch>=2.6.0
Requires-Dist: numpy>=1.24.0
Requires-Dist: alphashape
Requires-Dist: psutil
Requires-Dist: tqdm
Requires-Dist: matplotlib
Requires-Dist: pyyaml
Requires-Dist: scikit-learn
Provides-Extra: all
Requires-Dist: treams; extra == "all"
Requires-Dist: pymiecs; extra == "all"
Requires-Dist: jupyterlab>=3; extra == "all"
Requires-Dist: ipywidgets; extra == "all"
Requires-Dist: pyvista[all,trame]; extra == "all"
Provides-Extra: test
Requires-Dist: treams; extra == "test"
Requires-Dist: pymiecs; extra == "test"
Requires-Dist: pytest; extra == "test"
Dynamic: license-file
